lora_pytorch/__init__.py
lora_pytorch/lora.py
lora_pytorch/modules/__init__.py
lora_pytorch/modules/attention.py
lora_pytorch/modules/base.py
lora_pytorch/modules/conv.py
lora_pytorch/modules/embedding.py
lora_pytorch/modules/linear.py
lora_pytorch-0.2.0.dist-info/LICENSE
lora_pytorch-0.2.0.dist-info/METADATA
lora_pytorch-0.2.0.dist-info/WHEEL
lora_pytorch-0.2.0.dist-info/top_level.txt
lora_pytorch-0.2.0.dist-info/RECORD
