Metadata-Version: 2.1
Name: lora-pytorch
Version: 0.2.0
Summary: project_description
Home-page: https://github.com/fkodom/lora-pytorch
Author: Frank Odom
Author-email: frank.odom.iii@gmail.com
Classifier: Programming Language :: Python :: 3
Classifier: Operating System :: OS Independent
Requires-Python: >=3.8
License-File: LICENSE
Requires-Dist: torch <3.0.0,>=1.7.0
Provides-Extra: all
Requires-Dist: black ==23.12.0 ; extra == 'all'
Requires-Dist: flake8 ; extra == 'all'
Requires-Dist: isort ; extra == 'all'
Requires-Dist: mypy ==1.8.0 ; extra == 'all'
Requires-Dist: pytest ; extra == 'all'
Requires-Dist: pytest-cov ; extra == 'all'
Requires-Dist: torchtext ; extra == 'all'
Requires-Dist: torchvision ; extra == 'all'
Requires-Dist: pre-commit ; extra == 'all'
Provides-Extra: dev
Requires-Dist: pre-commit ; extra == 'dev'
Requires-Dist: black ==23.12.0 ; extra == 'dev'
Requires-Dist: flake8 ; extra == 'dev'
Requires-Dist: isort ; extra == 'dev'
Requires-Dist: mypy ==1.8.0 ; extra == 'dev'
Requires-Dist: pytest ; extra == 'dev'
Requires-Dist: pytest-cov ; extra == 'dev'
Requires-Dist: torchtext ; extra == 'dev'
Requires-Dist: torchvision ; extra == 'dev'
Provides-Extra: test
Requires-Dist: black ==23.12.0 ; extra == 'test'
Requires-Dist: flake8 ; extra == 'test'
Requires-Dist: isort ; extra == 'test'
Requires-Dist: mypy ==1.8.0 ; extra == 'test'
Requires-Dist: pytest ; extra == 'test'
Requires-Dist: pytest-cov ; extra == 'test'
Requires-Dist: torchtext ; extra == 'test'
Requires-Dist: torchvision ; extra == 'test'
